adminextensions/__init__.py
adminextensions/admin.py
adminextensions/list_display.py
adminextensions/object_tools.py
adminextensions/shortcuts.py
adminextensions/utils.py
adminextensions/version.py
adminextensions/templates/adminextensions/change_form.html
adminextensions/templates/adminextensions/change_list.html
adminextensions/templatetags/__init__.py
adminextensions/templatetags/admin_extensions.py
django_admin_extensions-0.10.0.dist-info/DESCRIPTION.rst
django_admin_extensions-0.10.0.dist-info/METADATA
django_admin_extensions-0.10.0.dist-info/RECORD
django_admin_extensions-0.10.0.dist-info/WHEEL
django_admin_extensions-0.10.0.dist-info/metadata.json
django_admin_extensions-0.10.0.dist-info/top_level.txt
tests/__init__.py
tests/test_admin.py
tests/test_list_display.py
tests/test_object_tools.py
tests/test_shortcuts.py
tests/test_utils.py
tests/app/__init__.py
tests/app/admin.py
tests/app/models.py
tests/app/settings.py
tests/app/urls.py
