Metadata-Version: 2.0
Name: django-admin-extensions
Version: 0.10.0
Summary: Simple tools to extend the django admin site
Home-page: https://bitbucket.org/tim_heap/django-admin-extensions
Author: Tim Heap
Author-email: tim@timheap.me
License: UNKNOWN
Platform: UNKNOWN
Classifier: Environment :: Web Environment
Classifier: Intended Audience :: Developers
Classifier: Operating System :: OS Independent
Classifier: Programming Language :: Python
Classifier: Programming Language :: Python :: 2
Classifier: Programming Language :: Python :: 2.7
Classifier: Programming Language :: Python :: 3
Classifier: Programming Language :: Python :: 3.4
Classifier: Programming Language :: Python :: 3.5
Classifier: Programming Language :: Python
Classifier: Framework :: Django
Requires-Dist: Django (>=1.9)
